{
    "artwork_id": "artwork_20260104_002602_865",
    "style": "Impressionism",
    "object_names": [
        "mare"
    ],
    "detections": [
        {
            "box": [
                100.72881317138672,
                36.06328201293945,
                1022.4375,
                945.9052734375
            ],
            "confidence": 0.9521124958992004,
            "phrase": "horse"
        }
    ],
    "detection_count": 1,
    "confidence_threshold": 0.25,
    "timestamp": "2026-01-06T21:14:27.000041"
}