{
    "artwork_id": "artwork_20260103_235450_670",
    "style": "Impressionism",
    "object_names": [
        "picnic basket",
        "horse",
        "stand",
        "toy"
    ],
    "detections": [
        {
            "box": [
                240.53533935546875,
                30.6903076171875,
                889.8986206054688,
                819.3626098632812
            ],
            "confidence": 0.8460061550140381,
            "phrase": "horse"
        },
        {
            "box": [
                310.13568115234375,
                523.94140625,
                393.3175048828125,
                581.9501953125
            ],
            "confidence": 0.11699867248535156,
            "phrase": "toy"
        },
        {
            "box": [
                230.64266967773438,
                526.0765991210938,
                403.5622253417969,
                649.1932983398438
            ],
            "confidence": 0.6609548926353455,
            "phrase": "toy"
        },
        {
            "box": [
                743.4801635742188,
                646.8089599609375,
                791.5419311523438,
                664.3231201171875
            ],
            "confidence": 0.10468411445617676,
            "phrase": "toy"
        },
        {
            "box": [
                205.80572509765625,
                616.7916870117188,
                446.26361083984375,
                994.4552612304688
            ],
            "confidence": 0.2653946280479431,
            "phrase": "stand"
        },
        {
            "box": [
                592.56494140625,
                650.0929565429688,
                883.8209228515625,
                825.6301879882812
            ],
            "confidence": 0.1798776388168335,
            "phrase": "picnic basket"
        },
        {
            "box": [
                483.62890625,
                646.7022094726562,
                880.7794189453125,
                1005.4951782226562
            ],
            "confidence": 0.7911264300346375,
            "phrase": "picnic basket"
        },
        {
            "box": [
                483.41998291015625,
                782.4773559570312,
                823.5098266601562,
                1003.5187377929688
            ],
            "confidence": 0.14509443938732147,
            "phrase": "picnic basket"
        }
    ],
    "detection_count": 8,
    "confidence_threshold": 0.1,
    "timestamp": "2026-01-06T21:15:30.407936"
}