{
    "artwork_id": "artwork_20260103_233619_850",
    "style": "Impressionism",
    "object_names": [
        "blanket",
        "cat",
        "tray",
        "chocolate cake"
    ],
    "detections": [
        {
            "box": [
                49.00234603881836,
                132.3971710205078,
                548.21435546875,
                573.3895874023438
            ],
            "confidence": 0.9319164752960205,
            "phrase": "cat"
        },
        {
            "box": [
                585.5050048828125,
                450.18292236328125,
                871.6307983398438,
                683.1972045898438
            ],
            "confidence": 0.7936879992485046,
            "phrase": "cake"
        },
        {
            "box": [
                3.941601514816284,
                100.21142578125,
                1020.2120971679688,
                1020.8982543945312
            ],
            "confidence": 0.7732389569282532,
            "phrase": "bed"
        },
        {
            "box": [
                585.275390625,
                449.76763916015625,
                871.4248046875,
                682.8511352539062
            ],
            "confidence": 0.5543304681777954,
            "phrase": "bowl"
        }
    ],
    "detection_count": 4,
    "confidence_threshold": 0.25,
    "timestamp": "2026-01-06T01:07:01.010155"
}