{
    "artwork_id": "artwork_20260103_200425_688",
    "style": "Impressionism",
    "object_names": [
        "bed frame"
    ],
    "detections": [
        {
            "box": [
                542.3431396484375,
                189.1261444091797,
                938.36279296875,
                566.902587890625
            ],
            "confidence": 0.3077145516872406,
            "phrase": "bed frame"
        },
        {
            "box": [
                131.0226287841797,
                347.6349792480469,
                636.2821655273438,
                826.7669677734375
            ],
            "confidence": 0.26775288581848145,
            "phrase": "bed frame"
        },
        {
            "box": [
                126.990234375,
                192.135498046875,
                943.7926025390625,
                874.281005859375
            ],
            "confidence": 0.664097011089325,
            "phrase": "bed frame"
        }
    ],
    "detection_count": 3,
    "confidence_threshold": 0.1,
    "timestamp": "2026-01-06T00:56:55.128792"
}