{
  "artwork_id": "artwork_20260104_003918_530",
  "style": "impressionism",
  "object_names": [
    "church bench",
    "clock"
  ],
  "detections": [
    {
      "box": [
        41.667633056640625,
        208.90179443359375,
        890.8941650390625,
        1001.4671020507812
      ],
      "confidence": 0.5032156705856323,
      "phrase": "church bench"
    },
    {
      "box": [
        835,
        359.125,
        949,
        493.125
      ],
      "confidence": 1,
      "phrase": "clock"
    }
  ],
  "detection_count": 2,
  "model": "GroundingDINO",
  "timestamp": "2026-01-07T17:11:38.047Z"
}