{
    "artwork_id": "artwork_20260103_202113_669",
    "style": "Impressionism",
    "object_names": [
        "bowl",
        "cake",
        "mule"
    ],
    "detections": [
        {
            "box": [
                434.80841064453125,
                154.25384521484375,
                668.7808227539062,
                291.1434326171875
            ],
            "confidence": 0.6857023239135742,
            "phrase": "cake"
        },
        {
            "box": [
                665.8136596679688,
                195.9951934814453,
                832.1680297851562,
                303.2368469238281
            ],
            "confidence": 0.6641144752502441,
            "phrase": "bowl"
        }
    ],
    "detection_count": 2,
    "confidence_threshold": 0.3,
    "timestamp": "2026-01-06T01:01:42.979190"
}