{
    "artwork_id": "artwork_20260103_170340_851",
    "style": "Impressionism",
    "object_names": [
        "shopping bag",
        "banana",
        "sink",
        "backpack"
    ],
    "detections": [
        {
            "box": [
                375.96466064453125,
                142.18125915527344,
                570.2990112304688,
                457.962890625
            ],
            "confidence": 0.8942975997924805,
            "phrase": "banana"
        },
        {
            "box": [
                14.4407958984375,
                266.8351745605469,
                374.6669616699219,
                602.8693237304688
            ],
            "confidence": 0.7312375903129578,
            "phrase": "oven"
        },
        {
            "box": [
                241.41845703125,
                236.42236328125,
                316.7891540527344,
                280.59796142578125
            ],
            "confidence": 0.4634689390659332,
            "phrase": "bowl"
        },
        {
            "box": [
                0.17578125,
                149.1198272705078,
                1020.2761840820312,
                1018.6677856445312
            ],
            "confidence": 0.39881980419158936,
            "phrase": "dining table"
        },
        {
            "box": [
                0.0,
                588.5735473632812,
                1021.3777465820312,
                1019.6173706054688
            ],
            "confidence": 0.3607892096042633,
            "phrase": "dining table"
        },
        {
            "box": [
                869.0465698242188,
                317.2416687011719,
                1022.2584838867188,
                372.874267578125
            ],
            "confidence": 0.33332857489585876,
            "phrase": "sink"
        },
        {
            "box": [
                966.9970703125,
                253.6439971923828,
                1023.8701171875,
                331.5719299316406
            ],
            "confidence": 0.27755194902420044,
            "phrase": "cup"
        }
    ],
    "detection_count": 7,
    "confidence_threshold": 0.25,
    "timestamp": "2026-01-06T00:33:55.766473"
}