{
  "artwork_id": "artwork_20260104_030935_992",
  "style": "chinese_ink_painting",
  "object_names": [
    "scroll",
    "vase",
    "bull"
  ],
  "detections": [
    {
      "box": [
        828.1341552734375,
        527.7630615234375,
        985.3985595703125,
        973.015625
      ],
      "confidence": 0.6676989793777466,
      "phrase": "vase"
    },
    {
      "box": [
        426.3742980957031,
        500.85675048828125,
        980.828857421875,
        1003.1088256835938
      ],
      "confidence": 0.3874416649341583,
      "phrase": "scroll"
    },
    {
      "box": [
        28,
        11.125,
        923,
        780.125
      ],
      "confidence": 1,
      "phrase": "bull"
    }
  ],
  "detection_count": 3,
  "model": "GroundingDINO",
  "timestamp": "2026-01-07T21:45:23.346Z"
}