{
    "artwork_id": "artwork_20260103_135953_823",
    "style": "Chinese Ink Painting",
    "object_names": [
        "dog",
        "sheep",
        "canoe",
        "paper",
        "vase",
        "dining table"
    ],
    "detections": [
        {
            "box": [
                529.2798461914062,
                221.89195251464844,
                887.7914428710938,
                525.43408203125
            ],
            "confidence": 0.7916005253791809,
            "phrase": "sheep"
        },
        {
            "box": [
                325.3621520996094,
                383.3221130371094,
                476.7204284667969,
                577.594970703125
            ],
            "confidence": 0.6708635687828064,
            "phrase": "dog"
        },
        {
            "box": [
                777.5599975585938,
                463.1916198730469,
                893.4839477539062,
                665.1866455078125
            ],
            "confidence": 0.6852453351020813,
            "phrase": "vase"
        },
        {
            "box": [
                229.62266540527344,
                564.972412109375,
                718.1528930664062,
                745.246826171875
            ],
            "confidence": 0.19981396198272705,
            "phrase": "canoe"
        },
        {
            "box": [
                666.6038208007812,
                662.3749389648438,
                896.8067016601562,
                756.2639770507812
            ],
            "confidence": 0.1341480314731598,
            "phrase": "paper"
        },
        {
            "box": [
                485.08184814453125,
                659.8839721679688,
                894.6004028320312,
                856.5985717773438
            ],
            "confidence": 0.638411283493042,
            "phrase": "paper"
        },
        {
            "box": [
                4.02618408203125,
                486.04034423828125,
                1018.3179321289062,
                1024.527099609375
            ],
            "confidence": 0.5434898138046265,
            "phrase": "dining table"
        }
    ],
    "detection_count": 7,
    "confidence_threshold": 0.1,
    "timestamp": "2026-01-06T01:24:03.912966"
}