{
  "artwork_id": "artwork_20260103_212938_737",
  "style": "chinese_ink_painting",
  "object_names": [
    "book",
    "person",
    "toy",
    "canoe"
  ],
  "detections": [
    {
      "box": [
        415.0390319824219,
        105.136962890625,
        889.946533203125,
        726.125244140625
      ],
      "confidence": 0.8638704419136047,
      "phrase": "person"
    },
    {
      "box": [
        333.0787048339844,
        538.0805053710938,
        404.7721252441406,
        636.2180786132812
      ],
      "confidence": 0.8256464004516602,
      "phrase": "toy"
    },
    {
      "box": [
        469.1809997558594,
        458.14990234375,
        615.3863525390625,
        541.9226684570312
      ],
      "confidence": 0.5609156489372253,
      "phrase": "book"
    },
    {
      "box": [
        5,
        295.125,
        1018,
        935.125
      ],
      "confidence": 1,
      "phrase": "canoe"
    }
  ],
  "detection_count": 4,
  "model": "GroundingDINO",
  "timestamp": "2026-01-07T20:39:33.905Z"
}