{
    "artwork_id": "artwork_20260104_032637_554",
    "style": "Chinese Ink Painting",
    "object_names": [
        "rocking chair",
        "toy",
        "canoe"
    ],
    "detections": [
        {
            "box": [
                318.173828125,
                295.2928771972656,
                957.8324584960938,
                909.345703125
            ],
            "confidence": 0.820119321346283,
            "phrase": "chair"
        },
        {
            "box": [
                0.781750500202179,
                343.9114685058594,
                141.4174346923828,
                604.5269165039062
            ],
            "confidence": 0.6417208313941956,
            "phrase": "bed"
        },
        {
            "box": [
                140.2961883544922,
                61.192970275878906,
                1023.9016723632812,
                905.8173217773438
            ],
            "confidence": 0.4114540219306946,
            "phrase": "bed"
        },
        {
            "box": [
                144.5636749267578,
                64.3006362915039,
                1023.5771484375,
                404.41680908203125
            ],
            "confidence": 0.32175275683403015,
            "phrase": "bed"
        },
        {
            "box": [
                150.56370544433594,
                774.0888061523438,
                304.72552490234375,
                886.9576416015625
            ],
            "confidence": 0.31101369857788086,
            "phrase": "elephant"
        }
    ],
    "detection_count": 5,
    "confidence_threshold": 0.25,
    "timestamp": "2026-01-07T14:20:20.086442"
}