{
  "artwork_id": "artwork_20260104_030921_571",
  "style": "chinese_ink_painting",
  "object_names": [
    "sheep",
    "parrot",
    "clock",
    "dragon"
  ],
  "detections": [
    {
      "box": [
        207.84002685546875,
        335.77935791015625,
        799.7159423828125,
        950.1401977539062
      ],
      "confidence": 0.8317209482192993,
      "phrase": "sheep"
    },
    {
      "box": [
        388.2063293457031,
        133.281982421875,
        508.0794372558594,
        475.228759765625
      ],
      "confidence": 0.8409644961357117,
      "phrase": "parrot"
    },
    {
      "box": [
        431.385009765625,
        650.825927734375,
        612.4906005859375,
        992.3095703125
      ],
      "confidence": 0.43684378266334534,
      "phrase": "clock"
    },
    {
      "box": [
        -6,
        32.125,
        1014,
        836.125
      ],
      "confidence": 1,
      "phrase": "dragon"
    }
  ],
  "detection_count": 4,
  "model": "GroundingDINO",
  "timestamp": "2026-01-07T21:45:03.058Z"
}