{
    "artwork_id": "artwork_20260104_021738_255",
    "style": "Chinese Ink Painting",
    "object_names": [
        "apple",
        "book",
        "cat"
    ],
    "detections": [
        {
            "box": [
                404.47503662109375,
                69.98519897460938,
                1009.3877563476562,
                966.1256103515625
            ],
            "confidence": 0.7587965130805969,
            "phrase": "cat"
        },
        {
            "box": [
                241.90774536132812,
                542.7755126953125,
                416.4656066894531,
                736.2650146484375
            ],
            "confidence": 0.8388001322746277,
            "phrase": "apple"
        },
        {
            "box": [
                51.95893859863281,
                681.37841796875,
                550.2643432617188,
                877.922119140625
            ],
            "confidence": 0.5025982856750488,
            "phrase": "book"
        },
        {
            "box": [
                66.66450500488281,
                682.7892456054688,
                540.1300048828125,
                795.2639770507812
            ],
            "confidence": 0.18344205617904663,
            "phrase": "book"
        },
        {
            "box": [
                56.522247314453125,
                725.4044189453125,
                541.732177734375,
                876.443603515625
            ],
            "confidence": 0.21546663343906403,
            "phrase": "book"
        },
        {
            "box": [
                313.9637451171875,
                724.6715087890625,
                548.85986328125,
                851.789306640625
            ],
            "confidence": 0.10877301543951035,
            "phrase": "book"
        },
        {
            "box": [
                58.97814178466797,
                742.8101806640625,
                275.62994384765625,
                870.707275390625
            ],
            "confidence": 0.22902633249759674,
            "phrase": "book"
        },
        {
            "box": [
                58.652984619140625,
                747.97265625,
                544.997314453125,
                877.447265625
            ],
            "confidence": 0.24371547996997833,
            "phrase": "book"
        }
    ],
    "detection_count": 8,
    "confidence_threshold": 0.1,
    "timestamp": "2026-01-06T01:37:10.489198"
}