{
    "artwork_id": "artwork_20260103_211743_100",
    "style": "Chinese Ink Painting",
    "object_names": [
        "book",
        "paper plate",
        "table",
        "rocking chair"
    ],
    "detections": [
        {
            "box": [
                183.70751953125,
                416.0572204589844,
                372.81427001953125,
                524.8868408203125
            ],
            "confidence": 0.14365358650684357,
            "phrase": "book"
        },
        {
            "box": [
                258.4620666503906,
                451.1978454589844,
                431.1781921386719,
                547.9886474609375
            ],
            "confidence": 0.22813336551189423,
            "phrase": "book"
        },
        {
            "box": [
                502.20318603515625,
                157.87261962890625,
                1021.8823852539062,
                905.2008666992188
            ],
            "confidence": 0.26595979928970337,
            "phrase": "rocking chair"
        },
        {
            "box": [
                179.05186462402344,
                414.4029541015625,
                431.81549072265625,
                577.5362548828125
            ],
            "confidence": 0.5032714605331421,
            "phrase": "book"
        },
        {
            "box": [
                388.92449951171875,
                511.85986328125,
                625.2040405273438,
                630.4891357421875
            ],
            "confidence": 0.32387155294418335,
            "phrase": "paper plate"
        },
        {
            "box": [
                184.46441650390625,
                473.80023193359375,
                431.43743896484375,
                576.5989379882812
            ],
            "confidence": 0.20611540973186493,
            "phrase": "book"
        },
        {
            "box": [
                7.00518798828125,
                152.44757080078125,
                1016.568115234375,
                1016.6583862304688
            ],
            "confidence": 0.12372738867998123,
            "phrase": "rocking chair"
        },
        {
            "box": [
                187.16415405273438,
                492.1553955078125,
                424.8008117675781,
                580.9910888671875
            ],
            "confidence": 0.10264141112565994,
            "phrase": "book"
        },
        {
            "box": [
                -4.559326171875,
                368.23223876953125,
                754.6140747070312,
                837.6409301757812
            ],
            "confidence": 0.2960022985935211,
            "phrase": "table"
        },
        {
            "box": [
                -4.0201416015625,
                373.885009765625,
                749.3878784179688,
                1025.2879638671875
            ],
            "confidence": 0.5602768063545227,
            "phrase": "table"
        },
        {
            "box": [
                2.241668701171875,
                842.9885864257812,
                518.524658203125,
                1025.587890625
            ],
            "confidence": 0.16330759227275848,
            "phrase": "rocking chair"
        }
    ],
    "detection_count": 11,
    "confidence_threshold": 0.1,
    "timestamp": "2026-01-06T01:39:51.021147"
}