{
    "artwork_id": "artwork_20260103_151508_344",
    "style": "Baroque",
    "object_names": [
        "backpack",
        "paper",
        "bottle"
    ],
    "detections": [
        {
            "box": [
                788.3116455078125,
                469.5693359375,
                935.6819458007812,
                909.5343627929688
            ],
            "confidence": 0.875078022480011,
            "phrase": "bottle"
        },
        {
            "box": [
                106.6962890625,
                149.18310546875,
                875.8101806640625,
                896.2771606445312
            ],
            "confidence": 0.6351061463356018,
            "phrase": "vase"
        }
    ],
    "detection_count": 2,
    "confidence_threshold": 0.25,
    "timestamp": "2026-01-06T03:30:18.419434"
}