{
  "artwork_id": "artwork_20260103_195357_408",
  "style": "baroque",
  "object_names": [
    "baby elephant",
    "biscuit",
    "coffee cup"
  ],
  "detections": [
    {
      "box": [
        103.65219116210938,
        266.63580322265625,
        667.352294921875,
        862.5487670898438
      ],
      "confidence": 0.9235515594482422,
      "phrase": "baby elephant"
    },
    {
      "box": [
        685.82958984375,
        652.9732666015625,
        780.9061279296875,
        722.64453125
      ],
      "confidence": 0.6521421074867249,
      "phrase": "biscuit"
    },
    {
      "box": [
        603,
        694.125,
        894,
        908.125
      ],
      "confidence": 1,
      "phrase": "coffee cup"
    }
  ],
  "detection_count": 3,
  "model": "GroundingDINO",
  "timestamp": "2026-01-07T20:24:01.529Z"
}