{
  "artwork_id": "artwork_20260103_144029_610",
  "style": "baroque",
  "object_names": [
    "lion",
    "chariot",
    "ball"
  ],
  "detections": [
    {
      "box": [
        0.49554443359375,
        197.72268676757812,
        581.9120483398438,
        907.1005859375
      ],
      "confidence": 0.9029802680015564,
      "phrase": "lion"
    },
    {
      "box": [
        470,
        88.125,
        1014,
        881.125
      ],
      "confidence": 1,
      "phrase": "chariot"
    },
    {
      "box": [
        543,
        705.125,
        788,
        956.125
      ],
      "confidence": 1,
      "phrase": "ball"
    }
  ],
  "detection_count": 3,
  "model": "GroundingDINO",
  "timestamp": "2026-01-07T19:55:52.946Z"
}