{
    "artwork_id": "artwork_20260103_025138_439",
    "style": "Post-Impressionism",
    "object_names": [
        "doll",
        "sheep",
        "canopy",
        "dog"
    ],
    "detections": [
        {
            "box": [
                406.7055358886719,
                307.4808349609375,
                945.1646728515625,
                851.827392578125
            ],
            "confidence": 0.8663514256477356,
            "phrase": "sheep"
        },
        {
            "box": [
                66.34219360351562,
                505.3497314453125,
                447.6082458496094,
                985.857666015625
            ],
            "confidence": 0.7580370903015137,
            "phrase": "doll"
        }
    ],
    "detection_count": 2,
    "confidence_threshold": 0.3,
    "timestamp": "2026-01-07T14:41:45.538440"
}