{
    "artwork_id": "artwork_20260103_034900_781",
    "style": "Post-Impressionism",
    "object_names": [
        "violet",
        "mule",
        "lamb"
    ],
    "detections": [
        {
            "box": [
                141.677001953125,
                13.14849853515625,
                991.1668701171875,
                910.64404296875
            ],
            "confidence": 0.6798446178436279,
            "phrase": "mule"
        },
        {
            "box": [
                124.57064819335938,
                533.5291137695312,
                402.3320007324219,
                940.1543579101562
            ],
            "confidence": 0.8420543074607849,
            "phrase": "lamb"
        },
        {
            "box": [
                353.12811279296875,
                720.3926391601562,
                477.515625,
                815.2158813476562
            ],
            "confidence": 0.1710422933101654,
            "phrase": "violet"
        }
    ],
    "detection_count": 3,
    "confidence_threshold": 0.1,
    "timestamp": "2026-01-07T14:30:59.520842"
}