{
    "artwork_id": "artwork_20260103_032421_789",
    "style": "Post-Impressionism",
    "object_names": [
        "cart",
        "canopy",
        "stick"
    ],
    "detections": [
        {
            "box": [
                35.487091064453125,
                24.906982421875,
                971.913330078125,
                612.17919921875
            ],
            "confidence": 0.6955216526985168,
            "phrase": "canopy"
        },
        {
            "box": [
                33.591888427734375,
                41.0457763671875,
                969.5787353515625,
                970.6221313476562
            ],
            "confidence": 0.4660224914550781,
            "phrase": "cart"
        },
        {
            "box": [
                924.5905151367188,
                552.7845458984375,
                1006.7051391601562,
                818.2042236328125
            ],
            "confidence": 0.13825951516628265,
            "phrase": "stick"
        },
        {
            "box": [
                99.41513061523438,
                394.2680969238281,
                928.3673095703125,
                977.88134765625
            ],
            "confidence": 0.37646469473838806,
            "phrase": "cart"
        },
        {
            "box": [
                128.94915771484375,
                531.21044921875,
                893.073974609375,
                974.78173828125
            ],
            "confidence": 0.15687920153141022,
            "phrase": "cart"
        },
        {
            "box": [
                0.7928581237792969,
                844.44677734375,
                96.07513427734375,
                970.0911865234375
            ],
            "confidence": 0.11239155381917953,
            "phrase": "stick"
        }
    ],
    "detection_count": 6,
    "confidence_threshold": 0.1,
    "timestamp": "2026-01-07T14:53:46.810136"
}