{
    "artwork_id": "artwork_20260103_022039_885",
    "style": "Post-Impressionism",
    "object_names": [
        "sink",
        "watering can",
        "sheep"
    ],
    "detections": [
        {
            "box": [
                527.1817626953125,
                204.54736328125,
                851.8397216796875,
                467.41033935546875
            ],
            "confidence": 0.8006542325019836,
            "phrase": "sheep"
        },
        {
            "box": [
                3.51300048828125,
                358.8728942871094,
                968.4905395507812,
                984.8492431640625
            ],
            "confidence": 0.34197402000427246,
            "phrase": "sink"
        },
        {
            "box": [
                -6.287567138671875,
                384.1795654296875,
                608.0665283203125,
                711.1068115234375
            ],
            "confidence": 0.1946086883544922,
            "phrase": "sink"
        },
        {
            "box": [
                544.9389038085938,
                594.2178955078125,
                972.9507446289062,
                979.8961181640625
            ],
            "confidence": 0.726902186870575,
            "phrase": "watering can"
        },
        {
            "box": [
                665.5087890625,
                609.7171630859375,
                965.9854736328125,
                976.335205078125
            ],
            "confidence": 0.12237107753753662,
            "phrase": "watering can"
        }
    ],
    "detection_count": 5,
    "confidence_threshold": 0.1,
    "timestamp": "2026-01-06T02:04:19.159385"
}