{
    "artwork_id": "artwork_20260103_024316_838",
    "style": "Post-Impressionism",
    "object_names": [
        "bull",
        "man",
        "doll"
    ],
    "detections": [
        {
            "box": [
                57.7703857421875,
                0.861907958984375,
                1012.493896484375,
                783.7017822265625
            ],
            "confidence": 0.8520641326904297,
            "phrase": "bull"
        },
        {
            "box": [
                366.7149353027344,
                347.32257080078125,
                1016.90966796875,
                969.4177856445312
            ],
            "confidence": 0.8760105967521667,
            "phrase": "man"
        },
        {
            "box": [
                536.22705078125,
                810.7118530273438,
                839.480712890625,
                1002.2091674804688
            ],
            "confidence": 0.30540555715560913,
            "phrase": "doll"
        }
    ],
    "detection_count": 3,
    "confidence_threshold": 0.3,
    "timestamp": "2026-01-06T02:09:51.621204"
}