{
    "artwork_id": "artwork_20260103_020525_540",
    "style": "Post-Impressionism",
    "object_names": [
        "dog",
        "cat",
        "soup bowl",
        "cow"
    ],
    "detections": [
        {
            "box": [
                180.5906982421875,
                0.2939910888671875,
                500.604736328125,
                319.459228515625
            ],
            "confidence": 0.13381405174732208,
            "phrase": "cow"
        },
        {
            "box": [
                170.33050537109375,
                6.331787109375,
                1028.45751953125,
                687.7207641601562
            ],
            "confidence": 0.6286555528640747,
            "phrase": "cow"
        },
        {
            "box": [
                362.03179931640625,
                27.65985107421875,
                1031.45947265625,
                668.7377319335938
            ],
            "confidence": 0.16094672679901123,
            "phrase": "cow"
        },
        {
            "box": [
                37.47552490234375,
                177.68096923828125,
                635.1765747070312,
                922.4293823242188
            ],
            "confidence": 0.5182018876075745,
            "phrase": "dog"
        },
        {
            "box": [
                624.1068725585938,
                452.598876953125,
                976.3224487304688,
                956.1083984375
            ],
            "confidence": 0.650970458984375,
            "phrase": "cat"
        }
    ],
    "detection_count": 5,
    "confidence_threshold": 0.1,
    "timestamp": "2026-01-06T02:06:34.791603"
}