{
    "artwork_id": "artwork_20260103_024319_406",
    "style": "Post-Impressionism",
    "object_names": [
        "bear",
        "canopy"
    ],
    "detections": [
        {
            "box": [
                215.16461181640625,
                545.9141235351562,
                788.3016967773438,
                825.6596069335938
            ],
            "confidence": 0.8607381582260132,
            "phrase": "bear"
        }
    ],
    "detection_count": 1,
    "confidence_threshold": 0.3,
    "timestamp": "2026-01-06T02:01:23.357400"
}