{
    "artwork_id": "artwork_20260104_005523_927",
    "style": "Neoclassicism",
    "object_names": [
        "swing",
        "basin",
        "lily",
        "scroll"
    ],
    "detections": [
        {
            "box": [
                305.6348876953125,
                662.7022705078125,
                902.1063232421875,
                981.962890625
            ],
            "confidence": 0.7943410873413086,
            "phrase": "basin"
        },
        {
            "box": [
                102.28851318359375,
                0.292877197265625,
                487.36529541015625,
                604.521240234375
            ],
            "confidence": 0.7695891857147217,
            "phrase": "swing"
        },
        {
            "box": [
                479.4910888671875,
                715.9219360351562,
                671.264404296875,
                835.7825317382812
            ],
            "confidence": 0.6096770763397217,
            "phrase": "lily"
        }
    ],
    "detection_count": 3,
    "confidence_threshold": 0.3,
    "timestamp": "2026-01-07T15:34:37.110563"
}