{
    "artwork_id": "artwork_20260104_012117_463",
    "style": "Neoclassicism",
    "object_names": [
        "boy",
        "apple"
    ],
    "detections": [
        {
            "box": [
                146.5079345703125,
                0.533984363079071,
                879.3186645507812,
                899.7990112304688
            ],
            "confidence": 0.9450146555900574,
            "phrase": "person"
        },
        {
            "box": [
                389.6672058105469,
                779.2018432617188,
                614.23486328125,
                985.3455200195312
            ],
            "confidence": 0.8943207859992981,
            "phrase": "apple"
        },
        {
            "box": [
                2.10009765625,
                298.5484313964844,
                1017.2301025390625,
                1016.7694702148438
            ],
            "confidence": 0.5851201415061951,
            "phrase": "bed"
        },
        {
            "box": [
                1.5187500715255737,
                601.9658203125,
                1019.4552612304688,
                1021.7724609375
            ],
            "confidence": 0.2995242178440094,
            "phrase": "bed"
        }
    ],
    "detection_count": 4,
    "confidence_threshold": 0.25,
    "timestamp": "2026-01-07T15:28:08.979972"
}