{
    "artwork_id": "artwork_20260103_210602_914",
    "style": "Neoclassicism",
    "object_names": [
        "brooch",
        "comb",
        "sign",
        "dog"
    ],
    "detections": [
        {
            "box": [
                259.1856994628906,
                736.4016723632812,
                845.3626708984375,
                976.8571166992188
            ],
            "confidence": 0.4628201723098755,
            "phrase": "comb"
        }
    ],
    "detection_count": 1,
    "confidence_threshold": 0.3,
    "timestamp": "2026-01-07T15:57:15.491259"
}