{
    "artwork_id": "artwork_20260104_004714_836",
    "style": "Neoclassicism",
    "object_names": [
        "blanket",
        "blade",
        "dog"
    ],
    "detections": [
        {
            "box": [
                1.03125,
                522.94091796875,
                876.4946899414062,
                1022.1251220703125
            ],
            "confidence": 0.691222071647644,
            "phrase": "blanket"
        },
        {
            "box": [
                164.89837646484375,
                580.662841796875,
                792.8641357421875,
                951.8135986328125
            ],
            "confidence": 0.6510659456253052,
            "phrase": "blade"
        }
    ],
    "detection_count": 2,
    "confidence_threshold": 0.3,
    "timestamp": "2026-01-07T16:08:56.041763"
}